{
  "project_info": {
    "project_number": "63011117262",
    "firebase_url": "https://yourcf-90ea9.firebaseio.com",
    "project_id": "yourcf-90ea9",
    "storage_bucket": "yourcf-90ea9.appspot.com"
  },
  "client": [
    {
      "client_info": {
        "mobilesdk_app_id": "1:63011117262:android:8803ca4dd2d0e1b7",
        "android_client_info": {
          "package_name": "com.example.lorcan.yourcf"
        }
      },
      "oauth_client": [
        {
          "client_id": "63011117262-0j1jfsceilmnvpre1gkh16t01uo842pv.apps.googleusercontent.com",
          "client_type": 1,
          "android_info": {
            "package_name": "com.example.lorcan.yourcf",
            "certificate_hash": "66f46ea43b1de00746bf621a6d9560b163c139ea"
          }
        },
        {
          "client_id": "63011117262-m4s55979smhv9jdogvfgt6t9vbt00i8b.apps.googleusercontent.com",
          "client_type": 3
        }
      ],
      "api_key": [
        {
          "current_key": "AIzaSyD23Vi_ywcEtoS3bH_s1qZSXXCPcQ60Hig"
        }
      ],
      "services": {
        "analytics_service": {
          "status": 1
        },
        "appinvite_service": {
          "status": 2,
          "other_platform_oauth_client": [
            {
              "client_id": "63011117262-m4s55979smhv9jdogvfgt6t9vbt00i8b.apps.googleusercontent.com",
              "client_type": 3
            }
          ]
        },
        "ads_service": {
          "status": 2
        }
      }
    }
  ],
  "configuration_version": "1"
}